flexfl/__init__.py
flexfl/py.typed
flexfl/builtins/CommABC.py
flexfl/builtins/DatasetABC.py
flexfl/builtins/FederatedABC.py
flexfl/builtins/Logger.py
flexfl/builtins/MLFrameworkABC.py
flexfl/builtins/MessageABC.py
flexfl/builtins/NeuralNetworkABC.py
flexfl/builtins/Results.py
flexfl/builtins/WorkerManager.py
flexfl/cli/analysis.py
flexfl/cli/auto_restart.py
flexfl/cli/benchmark.py
flexfl/cli/division.py
flexfl/cli/fl.py
flexfl/cli/preprocess.py
flexfl/cli/utils.py
flexfl/comms/Kafka.py
flexfl/comms/MPI.py
flexfl/comms/MQTT.py
flexfl/comms/Zenoh.py
flexfl/datasets/Housing.py
flexfl/datasets/IOT_DNL.py
flexfl/datasets/Slicing5g.py
flexfl/datasets/TON_IOT.py
flexfl/datasets/UNSW.py
flexfl/datasets/_metadata/Housing.json
flexfl/datasets/_metadata/IOT_DNL.json
flexfl/datasets/_metadata/Slicing5g.json
flexfl/datasets/_metadata/TON_IOT.json
flexfl/datasets/_metadata/UNSW.json
flexfl/fl_algos/CentralizedAsync.py
flexfl/fl_algos/CentralizedSync.py
flexfl/fl_algos/DA_old.py
flexfl/fl_algos/DecentralizedAsync.py
flexfl/fl_algos/DecentralizedSync.py
flexfl/ml_fw/Keras.py
flexfl/ml_fw/PyTorch.py
flexfl/ml_fw/TensorFlow.py
flexfl/msg_layers/Raw.py
flexfl/neural_nets/IOT_DNL.py
flexfl/neural_nets/Slicing5g.py
flexfl/neural_nets/TON_IOT.py
flexfl/neural_nets/UNSW.py
flexfl/neural_nets/_metadata.json
flexfl-0.2.17.dist-info/METADATA
flexfl-0.2.17.dist-info/WHEEL
flexfl-0.2.17.dist-info/entry_points.txt
flexfl-0.2.17.dist-info/licenses/LICENSE
flexfl-0.2.17.dist-info/RECORD
